domaingistry/.gitignore
domaingistry/__init__.py
domaingistry/cli.py
domaingistry/domaingistry.py
domaingistry/__pycache__/__init__.cpython-36.pyc
domaingistry/__pycache__/domaingistry.cpython-36.pyc
domaingistry/test/__init__.py
domaingistry/test/test_cli.py
domaingistry/test/test_domaingistry.py
domaingistry-0.0.2.dist-info/LICENSE
domaingistry-0.0.2.dist-info/METADATA
domaingistry-0.0.2.dist-info/WHEEL
domaingistry-0.0.2.dist-info/entry_points.txt
domaingistry-0.0.2.dist-info/top_level.txt
domaingistry-0.0.2.dist-info/RECORD
