Metadata-Version: 2.1
Name: domaingistry
Version: 0.0.2
Summary: A Package For Generating Domain Names.
Home-page: https://github.com/Jcharis/python-domaingistry
Author: Jesse E.Agbe(JCharis)
Author-email: jcharistech@gmail.com
License: MIT
Platform: UNKNOWN
Classifier: License :: OSI Approved :: MIT License
Classifier: Programming Language :: Python :: 3
Classifier: Programming Language :: Python :: 3.7
Classifier: Operating System :: OS Independent
Requires-Dist: click
Requires-Dist: click-didyoumean
